<?xml version='1.0' encoding='utf-8'?>
<TextureAtlas imagePath="pogbot.png"><SubTexture name="pogbot Intro0000" x="0" y="0" width="1920" height="1080" frameX="0" frameY="0" frameWidth="1920" frameHeight="1080" />
<SubTexture name="pogbot Intro0001" x="1920" y="0" width="1920" height="1080" frameX="0" frameY="0" frameWidth="1920" frameHeight="1080" />
<SubTexture name="pogbot Intro0002" x="0" y="1080" width="1538" height="1080" frameX="0" frameY="0" frameWidth="1920" frameHeight="1080" />
<SubTexture name="pogbot Intro0003" x="1538" y="1080" width="1231" height="1080" frameX="0" frameY="0" frameWidth="1920" frameHeight="1080" />
<SubTexture name="pogbot Intro0004" x="0" y="2160" width="1171" height="1080" frameX="0" frameY="0" frameWidth="1920" frameHeight="1080" />
<SubTexture name="pogbot Intro0005" x="1171" y="2160" width="1619" height="1080" frameX="0" frameY="0" frameWidth="1920" frameHeight="1080" />
<SubTexture name="pogbot Intro0006" x="3840" y="0" width="1920" height="1080" frameX="0" frameY="0" frameWidth="1920" frameHeight="1080" />
<SubTexture name="pogbot Intro0007" x="3840" y="1080" width="1920" height="1080" frameX="0" frameY="0" frameWidth="1920" frameHeight="1080" />
<SubTexture name="pogbot Intro0008" x="3840" y="2160" width="1920" height="1080" frameX="0" frameY="0" frameWidth="1920" frameHeight="1080" />
<SubTexture name="pogbot Intro0009" x="0" y="3240" width="1920" height="1080" frameX="0" frameY="0" frameWidth="1920" frameHeight="1080" />
<SubTexture name="pogbot Intro0010" x="1920" y="3240" width="1920" height="1080" frameX="0" frameY="0" frameWidth="1920" frameHeight="1080" />
<SubTexture name="pogbot Intro0011" x="3840" y="3240" width="1920" height="1080" frameX="0" frameY="0" frameWidth="1920" frameHeight="1080" />
<SubTexture name="pogbot Intro0012" x="0" y="4320" width="1673" height="1080" frameX="0" frameY="0" frameWidth="1920" frameHeight="1080" />
<SubTexture name="pogbot Intro0013" x="1673" y="4320" width="1489" height="1080" frameX="-152" frameY="0" frameWidth="1920" frameHeight="1080" />
<SubTexture name="pogbot Intro0014" x="3162" y="4320" width="1079" height="1080" frameX="-387" frameY="0" frameWidth="1920" frameHeight="1080" />
<SubTexture name="pogbot Intro0015" x="2769" y="1080" width="789" height="1080" frameX="-534" frameY="0" frameWidth="1920" frameHeight="1080" />
<SubTexture name="pogbot Intro0016" x="2790" y="2160" width="632" height="989" frameX="-618" frameY="-48" frameWidth="1920" frameHeight="1080" />
<SubTexture name="pogbot Intro0017" x="7076" y="3614" width="543" height="851" frameX="-664" frameY="-118" frameWidth="1920" frameHeight="1080" />
<SubTexture name="pogbot Intro0018" x="0" y="6352" width="523" height="827" frameX="-673" frameY="-185" frameWidth="1920" frameHeight="1080" />
<SubTexture name="pogbot Intro0019" x="7076" y="5300" width="529" height="831" frameX="-661" frameY="-249" frameWidth="1920" frameHeight="1080" />
<SubTexture name="pogbot Intro0020" x="1118" y="6352" width="538" height="767" frameX="-640" frameY="-313" frameWidth="1920" frameHeight="1080" />
<SubTexture name="pogbot Intro0021" x="2826" y="6352" width="548" height="706" frameX="-618" frameY="-374" frameWidth="1920" frameHeight="1080" />
<SubTexture name="pogbot Intro0022" x="3374" y="6352" width="554" height="656" frameX="-602" frameY="-424" frameWidth="1920" frameHeight="1080" />
<SubTexture name="pogbot Intro0023" x="3928" y="6352" width="561" height="623" frameX="-596" frameY="-457" frameWidth="1920" frameHeight="1080" />
<SubTexture name="pogbot Intro0024" x="4489" y="6352" width="566" height="612" frameX="-601" frameY="-468" frameWidth="1920" frameHeight="1080" />
<SubTexture name="pogbot Intro0025" x="5760" y="4760" width="574" height="633" frameX="-609" frameY="-447" frameWidth="1920" frameHeight="1080" />
<SubTexture name="pogbot Intro0026" x="6418" y="5678" width="581" height="667" frameX="-613" frameY="-413" frameWidth="1920" frameHeight="1080" />
<SubTexture name="pogbot Intro0027" x="2244" y="6352" width="582" height="711" frameX="-616" frameY="-369" frameWidth="1920" frameHeight="1080" />
<SubTexture name="pogbot Intro0028" x="1656" y="6352" width="588" height="756" frameX="-613" frameY="-324" frameWidth="1920" frameHeight="1080" />
<SubTexture name="pogbot Intro0029" x="523" y="6352" width="595" height="797" frameX="-611" frameY="-283" frameWidth="1920" frameHeight="1080" />
<SubTexture name="pogbot Intro0030" x="7076" y="4465" width="601" height="835" frameX="-610" frameY="-245" frameWidth="1920" frameHeight="1080" />
<SubTexture name="pogbot Intro0031" x="7076" y="2746" width="609" height="868" frameX="-609" frameY="-212" frameWidth="1920" frameHeight="1080" />
<SubTexture name="pogbot Intro0032" x="7076" y="1847" width="617" height="899" frameX="-609" frameY="-181" frameWidth="1920" frameHeight="1080" />
<SubTexture name="pogbot Intro0033" x="7076" y="927" width="624" height="920" frameX="-610" frameY="-154" frameWidth="1920" frameHeight="1080" />
<SubTexture name="pogbot Intro0034" x="7076" y="0" width="632" height="927" frameX="-610" frameY="-131" frameWidth="1920" frameHeight="1080" />
<SubTexture name="pogbot Intro0035" x="6418" y="4744" width="640" height="934" frameX="-611" frameY="-111" frameWidth="1920" frameHeight="1080" />
<SubTexture name="pogbot Intro0036" x="6418" y="3803" width="646" height="941" frameX="-612" frameY="-95" frameWidth="1920" frameHeight="1080" />
<SubTexture name="pogbot Intro0037" x="6418" y="2856" width="652" height="947" frameX="-613" frameY="-82" frameWidth="1920" frameHeight="1080" />
<SubTexture name="pogbot Intro0038" x="4899" y="4320" width="657" height="952" frameX="-613" frameY="-73" frameWidth="1920" frameHeight="1080" />
<SubTexture name="pogbot Intro0039" x="4241" y="4320" width="658" height="953" frameX="-615" frameY="-68" frameWidth="1920" frameHeight="1080" />
<SubTexture name="pogbot Intro0040" x="5760" y="0" width="658" height="952" frameX="-615" frameY="-69" frameWidth="1920" frameHeight="1080" />
<SubTexture name="pogbot idle0000" x="5760" y="0" width="658" height="952" frameX="-615" frameY="-69" frameWidth="1920" frameHeight="1080" />
<SubTexture name="pogbot up0000" x="5760" y="952" width="658" height="952" frameX="-615" frameY="-69" frameWidth="1920" frameHeight="1080" />
<SubTexture name="pogbot up0001" x="5760" y="1904" width="658" height="952" frameX="-615" frameY="-69" frameWidth="1920" frameHeight="1080" />
<SubTexture name="pogbot up0002" x="5760" y="2856" width="658" height="952" frameX="-615" frameY="-69" frameWidth="1920" frameHeight="1080" />
<SubTexture name="pogbot up0003" x="5760" y="3808" width="658" height="952" frameX="-615" frameY="-69" frameWidth="1920" frameHeight="1080" />
<SubTexture name="pogbot up0004" x="5760" y="0" width="658" height="952" frameX="-615" frameY="-69" frameWidth="1920" frameHeight="1080" />
<SubTexture name="pogbot Down0000" x="0" y="5400" width="658" height="952" frameX="-615" frameY="-69" frameWidth="1920" frameHeight="1080" />
<SubTexture name="pogbot Down0001" x="658" y="5400" width="658" height="952" frameX="-615" frameY="-69" frameWidth="1920" frameHeight="1080" />
<SubTexture name="pogbot Down0002" x="1316" y="5400" width="658" height="952" frameX="-615" frameY="-69" frameWidth="1920" frameHeight="1080" />
<SubTexture name="pogbot Down0003" x="1974" y="5400" width="658" height="952" frameX="-615" frameY="-69" frameWidth="1920" frameHeight="1080" />
<SubTexture name="pogbot Down0004" x="5760" y="0" width="658" height="952" frameX="-615" frameY="-69" frameWidth="1920" frameHeight="1080" />
<SubTexture name="pogbot Left0000" x="2632" y="5400" width="658" height="952" frameX="-615" frameY="-69" frameWidth="1920" frameHeight="1080" />
<SubTexture name="pogbot Left0001" x="3290" y="5400" width="658" height="952" frameX="-615" frameY="-69" frameWidth="1920" frameHeight="1080" />
<SubTexture name="pogbot Left0002" x="3948" y="5400" width="658" height="952" frameX="-615" frameY="-69" frameWidth="1920" frameHeight="1080" />
<SubTexture name="pogbot Left0003" x="4606" y="5400" width="658" height="952" frameX="-615" frameY="-69" frameWidth="1920" frameHeight="1080" />
<SubTexture name="pogbot Left0004" x="5760" y="0" width="658" height="952" frameX="-615" frameY="-69" frameWidth="1920" frameHeight="1080" />
<SubTexture name="pogbot Right0000" x="5264" y="5400" width="658" height="952" frameX="-615" frameY="-69" frameWidth="1920" frameHeight="1080" />
<SubTexture name="pogbot Right0001" x="6418" y="0" width="658" height="952" frameX="-615" frameY="-69" frameWidth="1920" frameHeight="1080" />
<SubTexture name="pogbot Right0002" x="6418" y="952" width="658" height="952" frameX="-615" frameY="-69" frameWidth="1920" frameHeight="1080" />
<SubTexture name="pogbot Right0003" x="6418" y="1904" width="658" height="952" frameX="-615" frameY="-69" frameWidth="1920" frameHeight="1080" />
<SubTexture name="pogbot Right0004" x="5760" y="0" width="658" height="952" frameX="-615" frameY="-69" frameWidth="1920" frameHeight="1080" />
</TextureAtlas>
